Reserver/__init__.py
Reserver/controller.py
Reserver/main.py
Reserver/manifest.py
Reserver/model.py
Reserver/setting.py
Reserver/ui.py
Reserver/utils.py
Reserver/__pycache__/__init__.cpython-36.pyc
Reserver/__pycache__/utils.cpython-36.pyc
Reserver/static/bootstrap/dist/css/bootstrap-theme.css
Reserver/static/bootstrap/dist/css/bootstrap-theme.css.map
Reserver/static/bootstrap/dist/css/bootstrap-theme.min.css
Reserver/static/bootstrap/dist/css/bootstrap.css
Reserver/static/bootstrap/dist/css/bootstrap.css.map
Reserver/static/bootstrap/dist/css/bootstrap.min.css
Reserver/static/bootstrap/dist/js/bootstrap.js
Reserver/static/bootstrap/dist/js/bootstrap.min.js
Reserver/static/bootstrap/grunt/bs-glyphicons-data-generator.js
Reserver/static/bootstrap/grunt/bs-lessdoc-parser.js
Reserver/static/bootstrap/grunt/bs-raw-files-generator.js
Reserver/static/bootstrap/grunt/sauce_browsers.yml
Reserver/static/bootstrap/js/affix.js
Reserver/static/bootstrap/js/alert.js
Reserver/static/bootstrap/js/button.js
Reserver/static/bootstrap/js/carousel.js
Reserver/static/bootstrap/js/collapse.js
Reserver/static/bootstrap/js/dropdown.js
Reserver/static/bootstrap/js/modal.js
Reserver/static/bootstrap/js/popover.js
Reserver/static/bootstrap/js/scrollspy.js
Reserver/static/bootstrap/js/tab.js
Reserver/static/bootstrap/js/tooltip.js
Reserver/static/bootstrap/js/transition.js
Reserver/static/bootstrap/less/alerts.less
Reserver/static/bootstrap/less/badges.less
Reserver/static/bootstrap/less/bootstrap.less
Reserver/static/bootstrap/less/breadcrumbs.less
Reserver/static/bootstrap/less/button-groups.less
Reserver/static/bootstrap/less/buttons.less
Reserver/static/bootstrap/less/carousel.less
Reserver/static/bootstrap/less/close.less
Reserver/static/bootstrap/less/code.less
Reserver/static/bootstrap/less/component-animations.less
Reserver/static/bootstrap/less/dropdowns.less
Reserver/static/bootstrap/less/forms.less
no_mroy_1-0.0.3.dist-info/DESCRIPTION.rst
no_mroy_1-0.0.3.dist-info/METADATA
no_mroy_1-0.0.3.dist-info/RECORD
no_mroy_1-0.0.3.dist-info/WHEEL
no_mroy_1-0.0.3.dist-info/entry_points.txt
no_mroy_1-0.0.3.dist-info/metadata.json
no_mroy_1-0.0.3.dist-info/top_level.txt
