Metadata-Version: 2.0
Name: no-mroy-1
Version: 0.0.3
Summary: a msg plugins
Home-page: https://github.com/Qingluan/no-mroy-1.git
Author: Qing luan
Author-email: UNKNOWN
License: MIT
Platform: UNKNOWN
Requires-Dist: mroylib-min
Requires-Dist: tornado
Requires-Dist: qtornado
Requires-Dist: qqbot
